MANIFEST.in
README.rst
setup.py
tgext/__init__.py
tgext.debugbar.egg-info/PKG-INFO
tgext.debugbar.egg-info/SOURCES.txt
tgext.debugbar.egg-info/dependency_links.txt
tgext.debugbar.egg-info/entry_points.txt
tgext.debugbar.egg-info/namespace_packages.txt
tgext.debugbar.egg-info/not-zip-safe
tgext.debugbar.egg-info/requires.txt
tgext.debugbar.egg-info/top_level.txt
tgext/debugbar/__init__.py
tgext/debugbar/controller.py
tgext/debugbar/initialize.py
tgext/debugbar/utils.py
tgext/debugbar/sections/__init__.py
tgext/debugbar/sections/base.py
tgext/debugbar/sections/controllers.py
tgext/debugbar/sections/inventing.py
tgext/debugbar/sections/logmessages.py
tgext/debugbar/sections/mingorm.py
tgext/debugbar/sections/request_vars.py
tgext/debugbar/sections/sqla.py
tgext/debugbar/sections/timing.py
tgext/debugbar/sections/templates/__init__.py
tgext/debugbar/sections/templates/controllers.html
tgext/debugbar/sections/templates/inventing.html
tgext/debugbar/sections/templates/logging.html
tgext/debugbar/sections/templates/ming.html
tgext/debugbar/sections/templates/request.html
tgext/debugbar/sections/templates/sqla.html
tgext/debugbar/sections/templates/timing.html
tgext/debugbar/statics/TgGear.png
tgext/debugbar/statics/__init__.py
tgext/debugbar/statics/jquery.js
tgext/debugbar/statics/style.css
tgext/debugbar/templates/__init__.py
tgext/debugbar/templates/debugbar.html
tgext/debugbar/templates/perform_ming.html
tgext/debugbar/templates/perform_sql.html