Metadata-Version: 1.1
Name: tgext.debugbar
Version: 0.5.0
Summary: Provides debug toolbar for TurboGears2
Home-page: https://pypi.python.org/pypi/tgext.debugbar
Author: Alessandro Molina
Author-email: amol@turbogears.org
License: MIT
Keywords: turbogears2.widgets
Platform: UNKNOWN
Classifier: Environment :: Web Environment
Classifier: Topic :: Software Development :: Libraries :: Python Modules
Classifier: Framework :: TurboGears
